cptf/__init__.py
cptf/cog_personalization_deep_learning_model.py
cptf/cog_personalization_micro_task_fingerprinting.py
cognitivepersonalizationtaskfingerprinting-1.0.3.dist-info/LICENSE.txt
cognitivepersonalizationtaskfingerprinting-1.0.3.dist-info/METADATA
cognitivepersonalizationtaskfingerprinting-1.0.3.dist-info/WHEEL
cognitivepersonalizationtaskfingerprinting-1.0.3.dist-info/top_level.txt
cognitivepersonalizationtaskfingerprinting-1.0.3.dist-info/RECORD
