Metadata-Version: 2.1
Name: cognitivepersonalizationtaskfingerprinting
Version: 1.0.3
Summary: The source code and more information are published in the following repository: https://github.com/dennispaulino/TaskFingerprintingForCognitivePersonalizationOfWebTasksDesignPackage
Author-email: Dennis Paulino <dpaulino@utad.pt>
Project-URL: Homepage, https://github.com/dennispaulino/TaskFingerprintingForCognitivePersonalizationOfWebTasksDesignPackage
Classifier: Programming Language :: Python :: 3
Classifier: License :: OSI Approved :: MIT License
Classifier: Operating System :: OS Independent
Requires-Python: >=3.8
License-File: LICENSE.txt
